README.md
setup.cfg
setup.py
pyjma/__init__.py
pyjma/client.py
pyjma/earthquake.py
pyjma/heavy_rain.py
pyjma/typhoon.py
pyjma/util.py
pyjma/volcano.py
pyjma.egg-info/PKG-INFO
pyjma.egg-info/SOURCES.txt
pyjma.egg-info/dependency_links.txt
pyjma.egg-info/requires.txt
pyjma.egg-info/top_level.txt