Metadata-Version: 1.1
Name: pyjma
Version: 1.0.13
Summary: A Python Library for Japan Disaster Data Extraction
Home-page: https://github.com/liaocyintl/pyjma
Author: Chenyi Liao
Author-email: info@liaocy.net
License: MIT
Keywords: python disaster japan meteorological agency jma
Platform: UNKNOWN
Classifier: Development Status :: 4 - Beta
Classifier: Intended Audience :: Developers
Classifier: Topic :: Software Development :: Build Tools
Classifier: License :: OSI Approved :: MIT License
Classifier: Programming Language :: Python :: 3
Classifier: Programming Language :: Python :: 3.4
Classifier: Programming Language :: Python :: 3.5
Classifier: Programming Language :: Python :: 3.6
Classifier: Programming Language :: Python :: 3.7
Classifier: Programming Language :: Python :: 3.8
